{
  "source_article_id": 131848,
  "lemmas": [
    {
      "lemma": "termostatstyring",
      "hgno": 0,
      "pos": "NOUN",
      "source_lemma_id": 2979792,
      "is_sub_article": false,
      "primary_translation": "thermostatic regulation",
      "word_forms": [
        {
          "word_form": "termostatstyring",
          "tags_json": [
            "Masc",
            "f1,m1",
            "Sing",
            "Ind",
            "Fem"
          ],
          "pronunciation": []
        },
        {
          "word_form": "termostatstyringen",
          "tags_json": [
            "Masc",
            "f1,m1",
            "Sing",
            "Def"
          ],
          "pronunciation": []
        },
        {
          "word_form": "termostatstyringer",
          "tags_json": [
            "Masc",
            "f1,m1",
            "Plur",
            "Ind",
            "Fem"
          ],
          "pronunciation": []
        },
        {
          "word_form": "termostatstyringene",
          "tags_json": [
            "Masc",
            "f1,m1",
            "Plur",
            "Def",
            "Fem"
          ],
          "pronunciation": []
        },
        {
          "word_form": "termostatstyringa",
          "tags_json": [
            "Fem",
            "f1,m1",
            "Sing",
            "Def"
          ],
          "pronunciation": []
        }
      ],
      "audio": {
        "lemma": [
          {
            "type": "tts",
            "provider": "google",
            "voice": "nb-NO-Chirp3-HD-Aoede",
            "language_code": "nb-NO",
            "format": "mp3",
            "file": "b8273b989c56.mp3",
            "path": "audio/lemma/google/nb-NO-Chirp3-HD-Aoede/b8273b989c56.mp3",
            "url": "https://media.umebocchi.my.id/audio/lemma/google/nb-NO-Chirp3-HD-Aoede/b8273b989c56.mp3",
            "text": "termostatstyring",
            "source": "generated",
            "content_sha256": "e0204d5ad3be411b12827e8aa3ae05967b0c64829c20041c376f295cbfb5c340"
          }
        ]
      }
    }
  ],
  "cross_reference": null,
  "definitions": [
    {
      "text": "det å regulere temperaturen automatisk",
      "translation": "automatic temperature regulation",
      "examples": [
        "termostatstyring av radiatorene"
      ]
    }
  ]
}
