{
  "source_article_id": 21133,
  "lemmas": [
    {
      "lemma": "grunnenhet",
      "hgno": 0,
      "pos": "NOUN",
      "source_lemma_id": 24680,
      "is_sub_article": false,
      "primary_translation": "base unit",
      "word_forms": [
        {
          "word_form": "grunnenhet",
          "tags_json": [
            "Masc",
            "f1,m1",
            "Sing",
            "Ind",
            "Fem"
          ],
          "pronunciation": [
            {
              "sampa": "\"gru0$n@n$%he:t",
              "ipa": "틛gr툴n톛n틟he틣t",
              "tone": 1,
              "source": "nb_uttale"
            }
          ]
        },
        {
          "word_form": "grunnenheten",
          "tags_json": [
            "Masc",
            "f1,m1",
            "Sing",
            "Def"
          ],
          "pronunciation": [
            {
              "sampa": "\"gru0$n@n$%he:$tn=",
              "ipa": "틛gr툴n톛n틟he틣tn퍌",
              "tone": 1,
              "source": "nb_uttale"
            }
          ]
        },
        {
          "word_form": "grunnenheter",
          "tags_json": [
            "Masc",
            "f1,m1",
            "Plur",
            "Ind",
            "Fem"
          ],
          "pronunciation": [
            {
              "sampa": "\"gru0$n@n$%he:$t@r",
              "ipa": "틛gr툴n톛n틟he틣t톛r",
              "tone": 1,
              "source": "nb_uttale"
            }
          ]
        },
        {
          "word_form": "grunnenhetene",
          "tags_json": [
            "Masc",
            "f1,m1",
            "Plur",
            "Def",
            "Fem"
          ],
          "pronunciation": [
            {
              "sampa": "\"\"gru0$ne:n$%he:$tn=$@",
              "ipa": "틛gr툴ne틣n틟he틣tn퍌톛",
              "tone": 2,
              "source": "nb_uttale"
            }
          ]
        },
        {
          "word_form": "grunnenheta",
          "tags_json": [
            "Fem",
            "f1,m1",
            "Sing",
            "Def"
          ],
          "pronunciation": [
            {
              "sampa": "\"gru0$n@n$%he:$tA",
              "ipa": "틛gr툴n톛n틟he틣t톔",
              "tone": 1,
              "source": "nb_uttale"
            }
          ]
        }
      ],
      "audio": {
        "lemma": [
          {
            "type": "tts",
            "provider": "google",
            "voice": "nb-NO-Chirp3-HD-Aoede",
            "language_code": "nb-NO",
            "format": "mp3",
            "file": "8215717bbda6.mp3",
            "path": "audio/lemma/google/nb-NO-Chirp3-HD-Aoede/8215717bbda6.mp3",
            "url": "https://media.umebocchi.my.id/audio/lemma/google/nb-NO-Chirp3-HD-Aoede/8215717bbda6.mp3",
            "text": "grunnenhet",
            "source": "generated",
            "content_sha256": "b8adbde403093bce113e8a9fe7c677d476b71e3541f70aba5d6f66ee0a1713fa",
            "tone": 1
          }
        ]
      }
    }
  ],
  "cross_reference": null,
  "definitions": [
    {
      "text": "m친lenhet som danner grunnlaget for andre enheter i et system",
      "translation": "base unit of measurement that forms the foundation for other units in a system",
      "examples": [
        "systemet er basert p친 de sju grunnenhetene meter, kilogram, sekund, ampere, kelvin, mol og candela"
      ]
    }
  ]
}
