{
  "source_article_id": 31741,
  "lemmas": [
    {
      "lemma": "kortison",
      "hgno": 0,
      "pos": "NOUN",
      "source_lemma_id": 37321,
      "is_sub_article": false,
      "primary_translation": "cortisone",
      "word_forms": [
        {
          "word_form": "kortison",
          "tags_json": [
            "Neuter",
            "n1",
            "Sing",
            "Ind",
            "Plur"
          ],
          "pronunciation": [
            {
              "sampa": "kO$t`I$\"su:n",
              "ipa": "kɔʈɪˈsuːn",
              "tone": 1,
              "source": "nb_uttale"
            }
          ]
        },
        {
          "word_form": "kortisonet",
          "tags_json": [
            "Neuter",
            "n1",
            "Sing",
            "Def"
          ],
          "pronunciation": []
        },
        {
          "word_form": "kortisona",
          "tags_json": [
            "Neuter",
            "n1",
            "Plur",
            "Def"
          ],
          "pronunciation": []
        },
        {
          "word_form": "kortisonene",
          "tags_json": [
            "Neuter",
            "n1",
            "Plur",
            "Def"
          ],
          "pronunciation": []
        }
      ],
      "audio": {
        "lemma": [
          {
            "type": "tts",
            "provider": "google",
            "voice": "nb-NO-Chirp3-HD-Aoede",
            "language_code": "nb-NO",
            "format": "mp3",
            "file": "5610f9d75252.mp3",
            "path": "audio/lemma/google/nb-NO-Chirp3-HD-Aoede/5610f9d75252.mp3",
            "url": "https://media.umebocchi.my.id/audio/lemma/google/nb-NO-Chirp3-HD-Aoede/5610f9d75252.mp3",
            "text": "kortison",
            "source": "generated",
            "content_sha256": "236293292bbd69b28a7c3480367c6308e2226f18db92219cbb142e509fa5b89c",
            "tone": 1
          }
        ]
      }
    }
  ],
  "cross_reference": null,
  "definitions": [
    {
      "text": "hormon i binyrebarken eller framstilt syntetisk til medisinsk bruk",
      "translation": "hormone in the adrenal cortex or produced synthetically for medical use",
      "examples": []
    }
  ]
}
