{
  "source_article_id": 35174,
  "lemmas": [
    {
      "lemma": "likesæl",
      "hgno": 0,
      "pos": "ADJ",
      "source_lemma_id": 40934,
      "is_sub_article": false,
      "primary_translation": "indifferent",
      "word_forms": [
        {
          "word_form": "likesæl",
          "tags_json": [
            "a1",
            "Pos",
            "Masc/Fem",
            "Ind",
            "Sing"
          ],
          "pronunciation": [
            {
              "sampa": "\"\"li:$k@$%se:l",
              "ipa": "ˈlɪːkəˌseːl",
              "tone": 2,
              "source": "nb_uttale"
            }
          ]
        },
        {
          "word_form": "likesæle",
          "tags_json": [
            "a1",
            "Pos",
            "Plur",
            "Def",
            "Sing"
          ],
          "pronunciation": [
            {
              "sampa": "\"\"li:$k@$%se:$l@",
              "ipa": "ˈlɪːkəˌseːlə",
              "tone": 2,
              "source": "nb_uttale"
            }
          ]
        },
        {
          "word_form": "likesælt",
          "tags_json": [
            "a1",
            "Pos",
            "Neuter",
            "Ind",
            "Sing"
          ],
          "pronunciation": [
            {
              "sampa": "\"\"li:$k@$%se:lt",
              "ipa": "ˈlɪːkəˌseːlt",
              "tone": 2,
              "source": "nb_uttale"
            }
          ]
        }
      ],
      "audio": {
        "lemma": [
          {
            "type": "tts",
            "provider": "google",
            "voice": "nb-NO-Chirp3-HD-Aoede",
            "language_code": "nb-NO",
            "format": "mp3",
            "file": "24e88c23d37a.mp3",
            "path": "audio/lemma/google/nb-NO-Chirp3-HD-Aoede/24e88c23d37a.mp3",
            "url": "https://media.umebocchi.my.id/audio/lemma/google/nb-NO-Chirp3-HD-Aoede/24e88c23d37a.mp3",
            "text": "likesæl",
            "source": "generated",
            "content_sha256": "d7b8ef17569f2dc429df50ed0c33425ff6c68c3852e8fa3f14a03eacc24f113d",
            "tone": 2
          }
        ]
      }
    }
  ],
  "cross_reference": null,
  "definitions": [
    {
      "text": "likeglad, likegyldig",
      "translation": "indifferent, unconcerned",
      "examples": [
        "være likesæl med alt",
        "stirre likesælt ut vinduet"
      ]
    }
  ]
}
