{
  "source_article_id": 65646,
  "lemmas": [
    {
      "lemma": "utreist",
      "hgno": 0,
      "pos": "ADJ",
      "source_lemma_id": 75297,
      "is_sub_article": false,
      "primary_translation": "emigrated",
      "word_forms": [
        {
          "word_form": "utreist",
          "tags_json": [
            "a2",
            "Pos",
            "Masc/Fem",
            "Ind",
            "Sing",
            "Neuter"
          ],
          "pronunciation": [
            {
              "sampa": "\"}:$%tr{*I$st",
              "ipa": "ˈʉːˌtræ͡ɪst",
              "tone": 1,
              "source": "nb_uttale"
            }
          ]
        },
        {
          "word_form": "utreiste",
          "tags_json": [
            "a2",
            "Pos",
            "Plur",
            "Def",
            "Sing"
          ],
          "pronunciation": [
            {
              "sampa": "\"}:$%tr{*I$st@",
              "ipa": "ˈʉːˌtræ͡ɪstə",
              "tone": 1,
              "source": "nb_uttale"
            }
          ]
        }
      ],
      "audio": {
        "lemma": [
          {
            "type": "tts",
            "provider": "google",
            "voice": "nb-NO-Chirp3-HD-Aoede",
            "language_code": "nb-NO",
            "format": "mp3",
            "file": "705ba7f8a05d.mp3",
            "path": "audio/lemma/google/nb-NO-Chirp3-HD-Aoede/705ba7f8a05d.mp3",
            "url": "https://media.umebocchi.my.id/audio/lemma/google/nb-NO-Chirp3-HD-Aoede/705ba7f8a05d.mp3",
            "text": "utreist",
            "source": "generated",
            "content_sha256": "4787d67ea46eff2a087904e9ba451ea927e0f781d7d7211560eaf773b18d94e8",
            "tone": 1
          }
        ]
      }
    }
  ],
  "cross_reference": null,
  "definitions": [
    {
      "text": "som har reist ut (av landet)",
      "translation": "having traveled out (of the country)",
      "examples": []
    }
  ]
}
