{
  "source_article_id": 6670,
  "lemmas": [
    {
      "lemma": "bløtkoke",
      "hgno": 0,
      "pos": "VERB",
      "source_lemma_id": 7913,
      "is_sub_article": false,
      "primary_translation": "soft-boil",
      "word_forms": [
        {
          "word_form": "bløtkoke",
          "tags_json": [
            "v2",
            "Inf"
          ],
          "pronunciation": [
            {
              "sampa": "\"\"bl2:t$%ku:$k@",
              "ipa": "ˈbløːtˌkuːkə",
              "tone": 2,
              "source": "nb_uttale"
            }
          ]
        },
        {
          "word_form": "bløtkoker",
          "tags_json": [
            "v2",
            "Pres"
          ],
          "pronunciation": [
            {
              "sampa": "\"\"bl2:t$%ku:$k@r",
              "ipa": "ˈbløːtˌkuːkər",
              "tone": 2,
              "source": "nb_uttale"
            }
          ]
        },
        {
          "word_form": "bløtkokes",
          "tags_json": [
            "v2",
            "Inf",
            "Pass",
            "Pres"
          ],
          "pronunciation": [
            {
              "sampa": "\"\"bl2:t$%ku:$k@s",
              "ipa": "ˈbløːtˌkuːkəs",
              "tone": 2,
              "source": "nb_uttale"
            }
          ]
        },
        {
          "word_form": "bløtkokte",
          "tags_json": [
            "v2",
            "Past",
            "Adj",
            "<PerfPart>",
            "Def",
            "Sing",
            "Plur"
          ],
          "pronunciation": [
            {
              "sampa": "\"\"bl2:t$%ku:k$t@",
              "ipa": "ˈbløːtˌkuːktə",
              "tone": 2,
              "source": "nb_uttale"
            }
          ]
        },
        {
          "word_form": "bløtkokt",
          "tags_json": [
            "v2",
            "<PerfPart>",
            "Adj",
            "Neuter",
            "Ind",
            "Sing",
            "Masc/Fem"
          ],
          "pronunciation": [
            {
              "sampa": "\"\"bl2:t$%ku:kt",
              "ipa": "ˈbløːtˌkuːkt",
              "tone": 2,
              "source": "nb_uttale"
            }
          ]
        },
        {
          "word_form": "bløtkokende",
          "tags_json": [
            "v2",
            "Adj",
            "<PresPart>"
          ],
          "pronunciation": [
            {
              "sampa": "\"\"bl2:t$%ku:$k@$n@",
              "ipa": "ˈbløːtˌkuːkənə",
              "tone": 2,
              "source": "nb_uttale"
            }
          ]
        },
        {
          "word_form": "bløtkok",
          "tags_json": [
            "v2",
            "Imp"
          ],
          "pronunciation": [
            {
              "sampa": "\"\"bl2:t$%ku:k",
              "ipa": "ˈbløːtˌkuːk",
              "tone": 2,
              "source": "nb_uttale"
            }
          ]
        }
      ],
      "audio": {
        "lemma": [
          {
            "type": "tts",
            "provider": "google",
            "voice": "nb-NO-Chirp3-HD-Aoede",
            "language_code": "nb-NO",
            "format": "mp3",
            "file": "2db314a36e51.mp3",
            "path": "audio/lemma/google/nb-NO-Chirp3-HD-Aoede/2db314a36e51.mp3",
            "url": "https://media.umebocchi.my.id/audio/lemma/google/nb-NO-Chirp3-HD-Aoede/2db314a36e51.mp3",
            "text": "bløtkoke",
            "source": "generated",
            "content_sha256": "bfd47aaad25688ac4f1ccb3daa99a253efc3481c753bd4b7e8f6854475e76ef4",
            "tone": 2
          }
        ]
      }
    },
    {
      "lemma": "blautkoke",
      "hgno": 0,
      "pos": "VERB",
      "source_lemma_id": 7413,
      "is_sub_article": false,
      "primary_translation": "soft-boil",
      "word_forms": [
        {
          "word_form": "blautkoke",
          "tags_json": [
            "v2",
            "Inf"
          ],
          "pronunciation": [
            {
              "sampa": "\"\"blE*u0t$%ku:$k@",
              "ipa": "ˈblæ͡ʉtˌkuːkə",
              "tone": 2,
              "source": "nb_uttale"
            }
          ]
        },
        {
          "word_form": "blautkoker",
          "tags_json": [
            "v2",
            "Pres"
          ],
          "pronunciation": [
            {
              "sampa": "\"\"blE*u0t$%ku:$k@r",
              "ipa": "ˈblæ͡ʉtˌkuːkər",
              "tone": 2,
              "source": "nb_uttale"
            }
          ]
        },
        {
          "word_form": "blautkokes",
          "tags_json": [
            "v2",
            "Inf",
            "Pass",
            "Pres"
          ],
          "pronunciation": [
            {
              "sampa": "\"\"blE*u0t$%ku:$k@s",
              "ipa": "ˈblæ͡ʉtˌkuːkəs",
              "tone": 2,
              "source": "nb_uttale"
            }
          ]
        },
        {
          "word_form": "blautkokte",
          "tags_json": [
            "v2",
            "Past",
            "Adj",
            "<PerfPart>",
            "Def",
            "Sing",
            "Plur"
          ],
          "pronunciation": [
            {
              "sampa": "\"\"blE*u0t$%ku:k$t@",
              "ipa": "ˈblæ͡ʉtˌkuːktə",
              "tone": 2,
              "source": "nb_uttale"
            }
          ]
        },
        {
          "word_form": "blautkokt",
          "tags_json": [
            "v2",
            "<PerfPart>",
            "Adj",
            "Neuter",
            "Ind",
            "Sing",
            "Masc/Fem"
          ],
          "pronunciation": [
            {
              "sampa": "\"\"blE*u0t$%ku:kt",
              "ipa": "ˈblæ͡ʉtˌkuːkt",
              "tone": 2,
              "source": "nb_uttale"
            }
          ]
        },
        {
          "word_form": "blautkokende",
          "tags_json": [
            "v2",
            "Adj",
            "<PresPart>"
          ],
          "pronunciation": [
            {
              "sampa": "\"\"blE*u0t$%ku:$k@$n@",
              "ipa": "ˈblæ͡ʉtˌkuːkənə",
              "tone": 2,
              "source": "nb_uttale"
            }
          ]
        },
        {
          "word_form": "blautkok",
          "tags_json": [
            "v2",
            "Imp"
          ],
          "pronunciation": [
            {
              "sampa": "\"\"blE*u0t$%ku:k",
              "ipa": "ˈblæ͡ʉtˌkuːk",
              "tone": 2,
              "source": "nb_uttale"
            }
          ]
        }
      ],
      "audio": {
        "lemma": [
          {
            "type": "tts",
            "provider": "google",
            "voice": "nb-NO-Chirp3-HD-Aoede",
            "language_code": "nb-NO",
            "format": "mp3",
            "file": "296882331a11.mp3",
            "path": "audio/lemma/google/nb-NO-Chirp3-HD-Aoede/296882331a11.mp3",
            "url": "https://media.umebocchi.my.id/audio/lemma/google/nb-NO-Chirp3-HD-Aoede/296882331a11.mp3",
            "text": "blautkoke",
            "source": "generated",
            "content_sha256": "19cc17d948f6b9a3b1c57dc06c3264ee3751fdee766d5928649b8d3c5117e875",
            "tone": 2
          }
        ]
      }
    }
  ],
  "cross_reference": null,
  "definitions": [
    {
      "text": "koke (egg) så lite at plommen ikke blir fast",
      "translation": "boil (egg) so little that the yolk does not become firm",
      "examples": []
    },
    {
      "text": "til forskjell fra hardkoke",
      "translation": "soft-boiled",
      "examples": []
    }
  ]
}
