{
  "source_article_id": 109368,
  "lemmas": [
    {
      "lemma": "bakerlære",
      "hgno": 0,
      "pos": "NOUN",
      "source_lemma_id": 162216,
      "is_sub_article": false,
      "primary_translation": "baker's apprenticeship",
      "word_forms": [
        {
          "word_form": "bakerlære",
          "tags_json": [
            "Masc",
            "m1, f1",
            "Sing",
            "Ind",
            "Fem"
          ],
          "pronunciation": [
            {
              "sampa": null,
              "ipa": "bˈɑːkərlˌæːrə",
              "tone": 2,
              "source": "nb_g2p",
              "tone_status": "known",
              "tone_label": "Accent 2",
              "prosody_trusted": false,
              "needs_review": true
            }
          ]
        },
        {
          "word_form": "bakerlæren",
          "tags_json": [
            "Masc",
            "m1, f1",
            "Sing",
            "Def"
          ],
          "pronunciation": [
            {
              "sampa": null,
              "ipa": "bˈɑːkərlˌæːɳ̩",
              "tone": 2,
              "source": "nb_g2p",
              "tone_status": "known",
              "tone_label": "Accent 2",
              "prosody_trusted": false,
              "needs_review": true
            }
          ]
        },
        {
          "word_form": "bakerlærer",
          "tags_json": [
            "Masc",
            "m1, f1",
            "Plur",
            "Ind",
            "Fem"
          ],
          "pronunciation": [
            {
              "sampa": null,
              "ipa": "bˈɑːkərlˌæːrər",
              "tone": 2,
              "source": "nb_g2p",
              "tone_status": "known",
              "tone_label": "Accent 2",
              "prosody_trusted": false,
              "needs_review": true
            }
          ]
        },
        {
          "word_form": "bakerlærene",
          "tags_json": [
            "Masc",
            "m1, f1",
            "Plur",
            "Def",
            "Fem"
          ],
          "pronunciation": [
            {
              "sampa": null,
              "ipa": "bˈɑːkərlˌæːɳ̩ə",
              "tone": 2,
              "source": "nb_g2p",
              "tone_status": "known",
              "tone_label": "Accent 2",
              "prosody_trusted": false,
              "needs_review": true
            }
          ]
        },
        {
          "word_form": "bakerlæra",
          "tags_json": [
            "Fem",
            "m1, f1",
            "Sing",
            "Def"
          ],
          "pronunciation": [
            {
              "sampa": null,
              "ipa": "bˈɑːkərlˌæːrɑ",
              "tone": 2,
              "source": "nb_g2p",
              "tone_status": "known",
              "tone_label": "Accent 2",
              "prosody_trusted": false,
              "needs_review": true
            }
          ]
        }
      ],
      "audio": {
        "lemma": [
          {
            "type": "tts",
            "provider": "google",
            "voice": "nb-NO-Chirp3-HD-Aoede",
            "language_code": "nb-NO",
            "format": "mp3",
            "file": "024ca4cac0d2.mp3",
            "path": "audio/lemma/google/nb-NO-Chirp3-HD-Aoede/024ca4cac0d2.mp3",
            "url": "https://media.umebocchi.my.id/audio/lemma/google/nb-NO-Chirp3-HD-Aoede/024ca4cac0d2.mp3",
            "text": "bakerlære",
            "source": "generated",
            "content_sha256": "124063a7c8253182dcaeda5ae6f0ce6178b9ec0c3fbc751ea2ec75a130497eb9"
          }
        ]
      }
    }
  ],
  "cross_reference": null,
  "definitions": [
    {
      "text": "tid i lære for å bli baker",
      "translation": "time as an apprentice to become a baker",
      "examples": [
        {
          "no": "gå i bakerlære",
          "en": "serve an apprenticeship as a baker"
        }
      ]
    }
  ]
}
