{
  "source_article_id": 11728,
  "lemmas": [
    {
      "lemma": "egenart",
      "hgno": 0,
      "pos": "NOUN",
      "source_lemma_id": 13670,
      "is_sub_article": false,
      "primary_translation": "distinctive quality / peculiarity",
      "word_forms": [
        {
          "word_form": "egenart",
          "tags_json": [
            "Masc",
            "m1, f1",
            "Sing",
            "Ind",
            "Fem"
          ],
          "pronunciation": [
            {
              "sampa": "\"\"e:$g@$%nAt`",
              "ipa": "틛e틣g톛틟n톔툳",
              "tone": 2,
              "source": "nb_uttale",
              "tone_status": "known",
              "tone_label": "Accent 2"
            }
          ]
        },
        {
          "word_form": "egenarten",
          "tags_json": [
            "Masc",
            "m1, f1",
            "Sing",
            "Def"
          ],
          "pronunciation": [
            {
              "sampa": "\"\"e:$g@$%nA$t`n`=",
              "ipa": "틛e틣g톛틟n톔툳톱퍌",
              "tone": 2,
              "source": "nb_uttale",
              "tone_status": "known",
              "tone_label": "Accent 2"
            }
          ]
        },
        {
          "word_form": "egenarter",
          "tags_json": [
            "Masc",
            "m1, f1",
            "Plur",
            "Ind",
            "Fem"
          ],
          "pronunciation": [
            {
              "sampa": "\"\"e:$g@$%nA$t`@r",
              "ipa": "틛e틣g톛틟n톔툳톛r",
              "tone": 2,
              "source": "nb_uttale",
              "tone_status": "known",
              "tone_label": "Accent 2"
            }
          ]
        },
        {
          "word_form": "egenartene",
          "tags_json": [
            "Masc",
            "m1, f1",
            "Plur",
            "Def",
            "Fem"
          ],
          "pronunciation": [
            {
              "sampa": "\"\"e:$g@$%nA$t`n`=$@",
              "ipa": "틛e틣g톛틟n톔툳톱퍌톛",
              "tone": 2,
              "source": "nb_uttale",
              "tone_status": "known",
              "tone_label": "Accent 2"
            }
          ]
        },
        {
          "word_form": "egenarta",
          "tags_json": [
            "Fem",
            "m1, f1",
            "Sing",
            "Def"
          ],
          "pronunciation": [
            {
              "sampa": "\"\"e:$g@$%nA$t`A",
              "ipa": "틛e틣g톛틟n톔툳톔",
              "tone": 2,
              "source": "nb_uttale",
              "tone_status": "known",
              "tone_label": "Accent 2"
            }
          ]
        }
      ],
      "audio": {
        "lemma": [
          {
            "type": "tts",
            "provider": "google",
            "voice": "nb-NO-Chirp3-HD-Aoede",
            "language_code": "nb-NO",
            "format": "mp3",
            "file": "16c885f7a8d0.mp3",
            "path": "audio/lemma/google/nb-NO-Chirp3-HD-Aoede/16c885f7a8d0.mp3",
            "url": "https://media.umebocchi.my.id/audio/lemma/google/nb-NO-Chirp3-HD-Aoede/16c885f7a8d0.mp3",
            "text": "egenart",
            "source": "generated",
            "content_sha256": "1b97f96a251eb7d6f8a4bbcab8fa4b93c10368b9a9e5492c5918ca587d73866e",
            "tone": 2
          }
        ]
      }
    },
    {
      "lemma": "eigenart",
      "hgno": 0,
      "pos": "NOUN",
      "source_lemma_id": 13834,
      "is_sub_article": false,
      "primary_translation": "distinctive quality / peculiarity",
      "word_forms": [
        {
          "word_form": "eigenart",
          "tags_json": [
            "Masc",
            "m1, f1",
            "Sing",
            "Ind",
            "Fem"
          ],
          "pronunciation": [
            {
              "sampa": "\"\"{*I$g@$%nA:t`",
              "ipa": "틛칝포톩g톛틟n톔틣툳",
              "tone": 2,
              "source": "nb_uttale",
              "tone_status": "known",
              "tone_label": "Accent 2"
            }
          ]
        },
        {
          "word_form": "eigenarten",
          "tags_json": [
            "Masc",
            "m1, f1",
            "Sing",
            "Def"
          ],
          "pronunciation": [
            {
              "sampa": "\"\"{*I$g@$%nA$t`n`=",
              "ipa": "틛칝포톩g톛틟n톔툳톱퍌",
              "tone": 2,
              "source": "nb_uttale",
              "tone_status": "known",
              "tone_label": "Accent 2"
            }
          ]
        },
        {
          "word_form": "eigenarter",
          "tags_json": [
            "Masc",
            "m1, f1",
            "Plur",
            "Ind",
            "Fem"
          ],
          "pronunciation": [
            {
              "sampa": "\"\"{*I$g@$%nA$t`@r",
              "ipa": "틛칝포톩g톛틟n톔툳톛r",
              "tone": 2,
              "source": "nb_uttale",
              "tone_status": "known",
              "tone_label": "Accent 2"
            }
          ]
        },
        {
          "word_form": "eigenartene",
          "tags_json": [
            "Masc",
            "m1, f1",
            "Plur",
            "Def",
            "Fem"
          ],
          "pronunciation": [
            {
              "sampa": "\"\"{*I$g@$%nA$t`n`=$@",
              "ipa": "틛칝포톩g톛틟n톔툳톱퍌톛",
              "tone": 2,
              "source": "nb_uttale",
              "tone_status": "known",
              "tone_label": "Accent 2"
            }
          ]
        },
        {
          "word_form": "eigenarta",
          "tags_json": [
            "Fem",
            "m1, f1",
            "Sing",
            "Def"
          ],
          "pronunciation": [
            {
              "sampa": "\"\"{*I$g@$%nA$t`A",
              "ipa": "틛칝포톩g톛틟n톔툳톔",
              "tone": 2,
              "source": "nb_uttale",
              "tone_status": "known",
              "tone_label": "Accent 2"
            }
          ]
        }
      ],
      "audio": {
        "lemma": [
          {
            "type": "tts",
            "provider": "google",
            "voice": "nb-NO-Chirp3-HD-Aoede",
            "language_code": "nb-NO",
            "format": "mp3",
            "file": "6ad9e01fbfb2.mp3",
            "path": "audio/lemma/google/nb-NO-Chirp3-HD-Aoede/6ad9e01fbfb2.mp3",
            "url": "https://media.umebocchi.my.id/audio/lemma/google/nb-NO-Chirp3-HD-Aoede/6ad9e01fbfb2.mp3",
            "text": "eigenart",
            "source": "generated",
            "content_sha256": "56010b60b2e1a3197f038efa2af7d7d563e1d7b1e62deeb4a1e739db701051e0",
            "tone": 2
          }
        ]
      }
    }
  ],
  "cross_reference": null,
  "definitions": [
    {
      "text": "karakteristisk preg",
      "translation": "characteristic feature",
      "examples": [
        {
          "no": "byggverkets egenart",
          "en": "the building's distinctive character"
        },
        {
          "no": "v친r nasjonale egenart",
          "en": "our national character"
        }
      ]
    }
  ]
}
