{
  "source_article_id": 22348,
  "lemmas": [
    {
      "lemma": "hangarskip",
      "hgno": 0,
      "pos": "NOUN",
      "source_lemma_id": 26199,
      "is_sub_article": false,
      "primary_translation": "aircraft carrier",
      "word_forms": [
        {
          "word_form": "hangarskip",
          "tags_json": [
            "Neuter",
            "n1",
            "Sing",
            "Ind",
            "Plur"
          ],
          "pronunciation": [
            {
              "sampa": "\"hAN$gA$%s`i:p",
              "ipa": "ňąh…ĎŇčg…ĎňĆ ā…™ňźp",
              "tone": 1,
              "source": "nb_uttale",
              "tone_status": "known",
              "tone_label": "Accent 1"
            }
          ]
        },
        {
          "word_form": "hangarskipet",
          "tags_json": [
            "Neuter",
            "n1",
            "Sing",
            "Def"
          ],
          "pronunciation": [
            {
              "sampa": "\"hAN$gA$%s`i:$p@",
              "ipa": "ňąh…ĎŇčg…ĎňĆ ā…™ňźp…ô",
              "tone": 1,
              "source": "nb_uttale",
              "tone_status": "known",
              "tone_label": "Accent 1"
            }
          ]
        },
        {
          "word_form": "hangarskipa",
          "tags_json": [
            "Neuter",
            "n1",
            "Plur",
            "Def"
          ],
          "pronunciation": [
            {
              "sampa": "\"hAN$gA$%s`i:$pA",
              "ipa": "ňąh…ĎŇčg…ĎňĆ ā…™ňźp…Ď",
              "tone": 1,
              "source": "nb_uttale",
              "tone_status": "known",
              "tone_label": "Accent 1"
            }
          ]
        },
        {
          "word_form": "hangarskipene",
          "tags_json": [
            "Neuter",
            "n1",
            "Plur",
            "Def"
          ],
          "pronunciation": [
            {
              "sampa": "\"hAN$gA$%s`i:$p@$n@",
              "ipa": "ňąh…ĎŇčg…ĎňĆ ā…™ňźp…ôn…ô",
              "tone": 1,
              "source": "nb_uttale",
              "tone_status": "known",
              "tone_label": "Accent 1"
            }
          ]
        }
      ],
      "audio": {
        "lemma": [
          {
            "type": "tts",
            "provider": "google",
            "voice": "nb-NO-Chirp3-HD-Aoede",
            "language_code": "nb-NO",
            "format": "mp3",
            "file": "a4a1cc3791e4.mp3",
            "path": "audio/lemma/google/nb-NO-Chirp3-HD-Aoede/a4a1cc3791e4.mp3",
            "url": "https://media.umebocchi.my.id/audio/lemma/google/nb-NO-Chirp3-HD-Aoede/a4a1cc3791e4.mp3",
            "text": "hangarskip",
            "source": "generated",
            "content_sha256": "e4c2b8bae83dfdd94cc9d26eaa5b495fe13431aaca7f8c01c727944a818cce87",
            "tone": 1
          }
        ]
      }
    }
  ],
  "cross_reference": null,
  "definitions": [
    {
      "text": "stort krigsskip som f√łrer fly (s√¶rlig jagerfly, lette bombefly og helikoptre) som kan starte og lande om bord",
      "translation": "large warship that carries aircraft (especially fighter planes, light bombers, and helicopters) that can take off and land on board",
      "examples": []
    }
  ]
}
