{
  "source_article_id": 2523,
  "lemmas": [
    {
      "lemma": "arbeidsglede",
      "hgno": 0,
      "pos": "NOUN",
      "source_lemma_id": 3054,
      "is_sub_article": false,
      "primary_translation": "joy of work",
      "word_forms": [
        {
          "word_form": "arbeidsglede",
          "tags_json": [
            "Masc",
            "m1, f1",
            "Sing",
            "Ind",
            "Fem"
          ],
          "pronunciation": [
            {
              "sampa": "\"\"Ar$b{*Id$%sgle:$d@",
              "ipa": "틛톔rb칝포톩d틟sgle틣d톛",
              "tone": 2,
              "source": "nb_uttale",
              "tone_status": "known",
              "tone_label": "Accent 2"
            }
          ]
        },
        {
          "word_form": "arbeidsgleden",
          "tags_json": [
            "Masc",
            "m1, f1",
            "Sing",
            "Def"
          ],
          "pronunciation": [
            {
              "sampa": "\"\"Ar$b{*Id$%sgle:$dn=",
              "ipa": "틛톔rb칝포톩d틟sgle틣dn퍌",
              "tone": 2,
              "source": "nb_uttale",
              "tone_status": "known",
              "tone_label": "Accent 2"
            }
          ]
        },
        {
          "word_form": "arbeidsgleder",
          "tags_json": [
            "Masc",
            "m1, f1",
            "Plur",
            "Ind",
            "Fem"
          ],
          "pronunciation": [
            {
              "sampa": "\"\"Ar$b{*Id$%sgle:$d@r",
              "ipa": "틛톔rb칝포톩d틟sgle틣d톛r",
              "tone": 2,
              "source": "nb_uttale",
              "tone_status": "known",
              "tone_label": "Accent 2"
            }
          ]
        },
        {
          "word_form": "arbeidsgledene",
          "tags_json": [
            "Masc",
            "m1, f1",
            "Plur",
            "Def",
            "Fem"
          ],
          "pronunciation": [
            {
              "sampa": "\"\"Ar$b{*Id$%sgle:$dn=$@",
              "ipa": "틛톔rb칝포톩d틟sgle틣dn퍌톛",
              "tone": 2,
              "source": "nb_uttale",
              "tone_status": "known",
              "tone_label": "Accent 2"
            }
          ]
        },
        {
          "word_form": "arbeidsgleda",
          "tags_json": [
            "Fem",
            "m1, f1",
            "Sing",
            "Def"
          ],
          "pronunciation": [
            {
              "sampa": "\"\"Ar$b{*Id$%sgle:$dA",
              "ipa": "틛톔rb칝포톩d틟sgle틣d톔",
              "tone": 2,
              "source": "nb_uttale",
              "tone_status": "known",
              "tone_label": "Accent 2"
            }
          ]
        }
      ],
      "audio": {
        "lemma": [
          {
            "type": "tts",
            "provider": "google",
            "voice": "nb-NO-Chirp3-HD-Aoede",
            "language_code": "nb-NO",
            "format": "mp3",
            "file": "f7fcf4afc6ec.mp3",
            "path": "audio/lemma/google/nb-NO-Chirp3-HD-Aoede/f7fcf4afc6ec.mp3",
            "url": "https://media.umebocchi.my.id/audio/lemma/google/nb-NO-Chirp3-HD-Aoede/f7fcf4afc6ec.mp3",
            "text": "arbeidsglede",
            "source": "generated",
            "content_sha256": "4b1b49e80e35f09da1f503d6f32dd98a87a84d4c55422a3609aed7d4cc7d6c29",
            "tone": 2
          }
        ]
      }
    }
  ],
  "cross_reference": null,
  "definitions": [
    {
      "text": "glede ved 친 arbeide",
      "translation": "joy in working",
      "examples": [
        {
          "no": "ha stor arbeidsglede",
          "en": "take great joy in one's work"
        }
      ]
    }
  ]
}
