{
  "source_article_id": 40717,
  "lemmas": [
    {
      "lemma": "nett",
      "hgno": 2,
      "pos": "ADJ",
      "source_lemma_id": 47644,
      "is_sub_article": false,
      "primary_translation": "neat / small / comely / considerable / economical / stingy",
      "word_forms": [
        {
          "word_form": "nett",
          "tags_json": [
            "a2",
            "Pos",
            "Masc/Fem",
            "Ind",
            "Sing",
            "Neuter"
          ],
          "pronunciation": [
            {
              "sampa": "\"nEt",
              "ipa": "ˈnɛt",
              "tone": 1,
              "source": "nb_uttale",
              "tone_status": "known",
              "tone_label": "Accent 1"
            }
          ]
        },
        {
          "word_form": "nette",
          "tags_json": [
            "a2",
            "Pos",
            "Plur",
            "Def",
            "Sing"
          ],
          "pronunciation": [
            {
              "sampa": "\"\"nE$t@",
              "ipa": "ˈnɛtə",
              "tone": 2,
              "source": "nb_uttale",
              "tone_status": "known",
              "tone_label": "Accent 2"
            }
          ]
        },
        {
          "word_form": "nettere",
          "tags_json": [
            "a2",
            "Cmp"
          ],
          "pronunciation": [
            {
              "sampa": "\"\"nE$t@$r@",
              "ipa": "ˈnɛtərə",
              "tone": 2,
              "source": "nb_uttale",
              "tone_status": "known",
              "tone_label": "Accent 2"
            }
          ]
        },
        {
          "word_form": "nettest",
          "tags_json": [
            "a2",
            "Sup",
            "Ind"
          ],
          "pronunciation": [
            {
              "sampa": "\"nE$t@$st",
              "ipa": "ˈnɛtəst",
              "tone": 1,
              "source": "nb_uttale",
              "tone_status": "known",
              "tone_label": "Accent 1"
            }
          ]
        },
        {
          "word_form": "netteste",
          "tags_json": [
            "a2",
            "Sup",
            "Def"
          ],
          "pronunciation": [
            {
              "sampa": "\"\"nE$t@$st@",
              "ipa": "ˈnɛtəstə",
              "tone": 2,
              "source": "nb_uttale",
              "tone_status": "known",
              "tone_label": "Accent 2"
            }
          ]
        }
      ],
      "audio": {
        "lemma": [
          {
            "type": "tts",
            "provider": "google",
            "voice": "nb-NO-Chirp3-HD-Aoede",
            "language_code": "nb-NO",
            "format": "mp3",
            "file": "ed4a34db1629.mp3",
            "path": "audio/lemma/google/nb-NO-Chirp3-HD-Aoede/ed4a34db1629.mp3",
            "url": "https://media.umebocchi.my.id/audio/lemma/google/nb-NO-Chirp3-HD-Aoede/ed4a34db1629.mp3",
            "text": "nett",
            "source": "generated",
            "content_sha256": "36679fb37ebaea79f563342d50f72030ab3cd608af2379f91451bf15d0454441",
            "tone": 1
          }
        ]
      }
    }
  ],
  "cross_reference": null,
  "definitions": [
    {
      "text": "pen, velpleid velpleiet velpleia, ordentlig",
      "translation": "neat, well-groomed, tidy",
      "examples": [
        {
          "no": "et nett lite hus",
          "en": "a neat little house"
        },
        {
          "no": "en nett liten jente",
          "en": "a neat little girl"
        }
      ]
    },
    {
      "text": "liten og velproporsjonert",
      "translation": "small and well-proportioned",
      "examples": [
        {
          "no": "en nett figur",
          "en": "a neat figure"
        },
        {
          "no": "ha et nett vesen",
          "en": "have a neat appearance"
        }
      ]
    },
    {
      "text": "temmelig stor",
      "translation": "fairly large",
      "examples": []
    },
    {
      "text": "ikke ubetydelig",
      "translation": "not insignificant",
      "examples": [
        {
          "no": "en nett liten formue",
          "en": "a tidy little fortune"
        },
        {
          "no": "den nette sum av 5000 kr",
          "en": "the tidy sum of 5,000 kroner"
        },
        {
          "no": "være nett på det",
          "en": "be pretty close"
        }
      ]
    }
  ]
}
