{
  "source_article_id": 49151,
  "lemmas": [
    {
      "lemma": "rus",
      "hgno": 0,
      "pos": "NOUN",
      "source_lemma_id": 56436,
      "is_sub_article": false,
      "primary_translation": "intoxication / ecstasy",
      "word_forms": [
        {
          "word_form": "rus",
          "tags_json": [
            "Masc",
            "m1",
            "Sing",
            "Ind"
          ],
          "pronunciation": [
            {
              "sampa": "\"r}:s",
              "ipa": "ˈrʉːs",
              "tone": 1,
              "source": "nb_uttale",
              "tone_status": "known",
              "tone_label": "Accent 1"
            }
          ]
        },
        {
          "word_form": "rusen",
          "tags_json": [
            "Masc",
            "m1",
            "Sing",
            "Def"
          ],
          "pronunciation": [
            {
              "sampa": "\"\"r}:$sn=",
              "ipa": "ˈrʉːsn̩",
              "tone": 2,
              "source": "nb_uttale",
              "tone_status": "known",
              "tone_label": "Accent 2"
            }
          ]
        },
        {
          "word_form": "ruser",
          "tags_json": [
            "Masc",
            "m1",
            "Plur",
            "Ind"
          ],
          "pronunciation": [
            {
              "sampa": "\"\"r}:$s@r",
              "ipa": "ˈrʉːsər",
              "tone": 2,
              "source": "nb_uttale",
              "tone_status": "known",
              "tone_label": "Accent 2"
            }
          ]
        },
        {
          "word_form": "rusene",
          "tags_json": [
            "Masc",
            "m1",
            "Plur",
            "Def"
          ],
          "pronunciation": [
            {
              "sampa": "\"\"r}:$sn=$@",
              "ipa": "ˈrʉːsn̩ə",
              "tone": 2,
              "source": "nb_uttale",
              "tone_status": "known",
              "tone_label": "Accent 2"
            }
          ]
        }
      ],
      "audio": {
        "lemma": [
          {
            "type": "tts",
            "provider": "google",
            "voice": "nb-NO-Chirp3-HD-Aoede",
            "language_code": "nb-NO",
            "format": "mp3",
            "file": "c10e71b35d56.mp3",
            "path": "audio/lemma/google/nb-NO-Chirp3-HD-Aoede/c10e71b35d56.mp3",
            "url": "https://media.umebocchi.my.id/audio/lemma/google/nb-NO-Chirp3-HD-Aoede/c10e71b35d56.mp3",
            "text": "rus",
            "source": "generated",
            "content_sha256": "fc8a369c4f0128801d78ea8fcd6bfa84a695d8b1791bd5dc312a354bac872fb4",
            "tone": 1
          }
        ]
      }
    }
  ],
  "cross_reference": null,
  "definitions": [
    {
      "text": "tilstand med blant annet følelse av velvære, økt impulsivitet og nedsatt vurderingsevne, utløst av alkohol, narkotika eller annet rusmiddel",
      "translation": "state characterized by feelings of well-being, increased impulsivity, and impaired judgment, triggered by alcohol, drugs, or other intoxicants",
      "examples": [
        {
          "no": "få seg en rus",
          "en": "have a drink"
        },
        {
          "no": "sove ut rusen",
          "en": "sleep it off"
        },
        {
          "no": "leve et liv i rus",
          "en": "live a life of substance abuse"
        },
        {
          "no": "slite med rus og traumer",
          "en": "struggle with substance abuse and trauma"
        }
      ]
    },
    {
      "text": "oppstemt sinnstilstand",
      "translation": "elated state of mind",
      "examples": [
        {
          "no": "i begeistringens rus",
          "en": "in the intoxication of enthusiasm"
        }
      ]
    }
  ]
}
