{
  "source_article_id": 5003,
  "lemmas": [
    {
      "lemma": "beheng",
      "hgno": 0,
      "pos": "NOUN",
      "source_lemma_id": 5857,
      "is_sub_article": false,
      "primary_translation": "dog's long ear and hindquarter hair",
      "word_forms": [
        {
          "word_form": "beheng",
          "tags_json": [
            "Neuter",
            "n1",
            "Sing",
            "Ind",
            "Plur"
          ],
          "pronunciation": [
            {
              "sampa": "b@$\"hEN",
              "ipa": "bəˈhɛŋ",
              "tone": 1,
              "source": "nb_uttale",
              "tone_status": "known",
              "tone_label": "Accent 1"
            }
          ]
        },
        {
          "word_form": "behenget",
          "tags_json": [
            "Neuter",
            "n1",
            "Sing",
            "Def"
          ],
          "pronunciation": [
            {
              "sampa": "b@$\"hEN$@",
              "ipa": "bəˈhɛŋə",
              "tone": 1,
              "source": "nb_uttale",
              "tone_status": "known",
              "tone_label": "Accent 1"
            }
          ]
        },
        {
          "word_form": "behenga",
          "tags_json": [
            "Neuter",
            "n1",
            "Plur",
            "Def"
          ],
          "pronunciation": [
            {
              "sampa": "b@$\"hEN$A",
              "ipa": "bəˈhɛŋɑ",
              "tone": 1,
              "source": "nb_uttale",
              "tone_status": "known",
              "tone_label": "Accent 1"
            }
          ]
        },
        {
          "word_form": "behengene",
          "tags_json": [
            "Neuter",
            "n1",
            "Plur",
            "Def"
          ],
          "pronunciation": [
            {
              "sampa": "b@$\"hEN$@$n@",
              "ipa": "bəˈhɛŋənə",
              "tone": 1,
              "source": "nb_uttale",
              "tone_status": "known",
              "tone_label": "Accent 1"
            }
          ]
        }
      ],
      "audio": {
        "lemma": [
          {
            "type": "tts",
            "provider": "google",
            "voice": "nb-NO-Chirp3-HD-Aoede",
            "language_code": "nb-NO",
            "format": "mp3",
            "file": "3624a0518d83.mp3",
            "path": "audio/lemma/google/nb-NO-Chirp3-HD-Aoede/3624a0518d83.mp3",
            "url": "https://media.umebocchi.my.id/audio/lemma/google/nb-NO-Chirp3-HD-Aoede/3624a0518d83.mp3",
            "text": "beheng",
            "source": "generated",
            "content_sha256": "7962c10b9e7d1997bd8bb0866668851acc9503c758ec21c0e0856951d46969ef",
            "tone": 1
          }
        ]
      }
    }
  ],
  "cross_reference": null,
  "definitions": [
    {
      "text": "langt hårlag på ørene og baksiden av bein hos hund",
      "translation": "long coat of hair on the ears and hindquarters of a dog",
      "examples": []
    }
  ]
}
