{
  "source_article_id": 66288,
  "lemmas": [
    {
      "lemma": "valne",
      "hgno": 0,
      "pos": "VERB",
      "source_lemma_id": 76087,
      "is_sub_article": false,
      "primary_translation": "to become whale-like",
      "word_forms": [
        {
          "word_form": "valne",
          "tags_json": [
            "verb",
            "Inf",
            "Imp"
          ],
          "pronunciation": [
            {
              "sampa": "\"\"vA:l$n@",
              "ipa": "藞v蓱藧ln蓹",
              "tone": 2,
              "source": "nb_uttale",
              "tone_status": "known",
              "tone_label": "Accent 2"
            }
          ]
        },
        {
          "word_form": "valner",
          "tags_json": [
            "verb",
            "Pres"
          ],
          "pronunciation": [
            {
              "sampa": "\"\"vA:l$n@r",
              "ipa": "藞v蓱藧ln蓹r",
              "tone": 2,
              "source": "nb_uttale",
              "tone_status": "known",
              "tone_label": "Accent 2"
            }
          ]
        },
        {
          "word_form": "valnes",
          "tags_json": [
            "verb",
            "Inf",
            "Pass",
            "Pres"
          ],
          "pronunciation": [
            {
              "sampa": "\"\"vA:l$n@s",
              "ipa": "藞v蓱藧ln蓹s",
              "tone": 2,
              "source": "nb_uttale",
              "tone_status": "known",
              "tone_label": "Accent 2"
            }
          ]
        },
        {
          "word_form": "valna",
          "tags_json": [
            "verb",
            "Past",
            "<PerfPart>",
            "Adj",
            "Neuter",
            "Ind",
            "Sing",
            "Masc/Fem",
            "Def",
            "Plur"
          ],
          "pronunciation": [
            {
              "sampa": "\"\"vA:l$nA",
              "ipa": "藞v蓱藧ln蓱",
              "tone": 2,
              "source": "nb_uttale",
              "tone_status": "known",
              "tone_label": "Accent 2"
            }
          ]
        },
        {
          "word_form": "valnende",
          "tags_json": [
            "verb",
            "Adj",
            "<PresPart>"
          ],
          "pronunciation": [
            {
              "sampa": "\"\"vA:l$nn=$@",
              "ipa": "藞v蓱藧lnn泰蓹",
              "tone": 2,
              "source": "nb_uttale",
              "tone_status": "known",
              "tone_label": "Accent 2"
            }
          ]
        },
        {
          "word_form": "valn",
          "tags_json": [
            "verb",
            "Imp"
          ],
          "pronunciation": [
            {
              "sampa": "\"vA:ln",
              "ipa": "藞v蓱藧ln",
              "tone": 1,
              "source": "nb_uttale",
              "tone_status": "known",
              "tone_label": "Accent 1"
            }
          ]
        },
        {
          "word_form": "valnet",
          "tags_json": [
            "verb",
            "Past",
            "<PerfPart>",
            "Adj",
            "Neuter",
            "Ind",
            "Sing",
            "Masc/Fem"
          ],
          "pronunciation": [
            {
              "sampa": "\"\"vA:l$n@t",
              "ipa": "藞v蓱藧ln蓹t",
              "tone": 2,
              "source": "nb_uttale",
              "tone_status": "known",
              "tone_label": "Accent 2"
            }
          ]
        },
        {
          "word_form": "valnete",
          "tags_json": [
            "verb",
            "Adj",
            "<PerfPart>",
            "Def",
            "Sing",
            "Plur"
          ],
          "pronunciation": [
            {
              "sampa": "\"\"vA:l$n@$t@",
              "ipa": "藞v蓱藧ln蓹t蓹",
              "tone": 2,
              "source": "nb_uttale",
              "tone_status": "known",
              "tone_label": "Accent 2"
            }
          ]
        },
        {
          "word_form": "valnede",
          "tags_json": [
            "verb",
            "Adj",
            "<PerfPart>",
            "Def",
            "Sing",
            "Plur"
          ],
          "pronunciation": [
            {
              "sampa": null,
              "ipa": "蕥藞蓱藧ln蓹d蓹",
              "tone": 2,
              "source": "nb_g2p",
              "tone_status": "known",
              "tone_label": "Accent 2",
              "prosody_trusted": false,
              "needs_review": true
            }
          ]
        }
      ],
      "audio": {
        "lemma": [
          {
            "type": "tts",
            "provider": "google",
            "voice": "nb-NO-Chirp3-HD-Aoede",
            "language_code": "nb-NO",
            "format": "mp3",
            "file": "c171a4edc1f9.mp3",
            "path": "audio/lemma/google/nb-NO-Chirp3-HD-Aoede/c171a4edc1f9.mp3",
            "url": "https://media.umebocchi.my.id/audio/lemma/google/nb-NO-Chirp3-HD-Aoede/c171a4edc1f9.mp3",
            "text": "valne",
            "source": "generated",
            "content_sha256": "920c8ecf062db10232f7a4bdf7f1614afd73a7ae3e9b339772c4c1cbe49d4ac9",
            "tone": 2
          }
        ]
      }
    }
  ],
  "cross_reference": null,
  "definitions": [
    {
      "text": "bli eller gj酶re valen",
      "translation": "",
      "examples": [
        {
          "no": "valne bort i fingrene",
          "en": "go numb in the fingers"
        }
      ]
    }
  ]
}
