{
  "source_article_id": 115473,
  "lemmas": [
    {
      "lemma": "gromunge",
      "hgno": 0,
      "pos": "NOUN",
      "source_lemma_id": 165454,
      "is_sub_article": false,
      "primary_translation": "favorite child",
      "word_forms": [
        {
          "word_form": "gromunge",
          "tags_json": [
            "Masc",
            "m1",
            "Sing",
            "Ind"
          ]
        },
        {
          "word_form": "gromungen",
          "tags_json": [
            "Masc",
            "m1",
            "Sing",
            "Def"
          ]
        },
        {
          "word_form": "gromunger",
          "tags_json": [
            "Masc",
            "m1",
            "Plur",
            "Ind"
          ]
        },
        {
          "word_form": "gromungene",
          "tags_json": [
            "Masc",
            "m1",
            "Plur",
            "Def"
          ]
        }
      ]
    }
  ],
  "cross_reference": null,
  "definitions": []
}