{
  "source_article_id": 121513,
  "lemmas": [
    {
      "lemma": "ettergå",
      "hgno": 0,
      "pos": "VERB",
      "source_lemma_id": 168913,
      "is_sub_article": false,
      "primary_translation": "scrutinize / examine closely",
      "word_forms": [
        {
          "word_form": "ettergå",
          "tags_json": [
            "verb",
            "Inf",
            "Imp"
          ]
        },
        {
          "word_form": "ettergår",
          "tags_json": [
            "verb",
            "Pres"
          ]
        },
        {
          "word_form": "ettergås",
          "tags_json": [
            "verb",
            "Inf",
            "Pass",
            "Pres"
          ]
        },
        {
          "word_form": "ettergikk",
          "tags_json": [
            "verb",
            "Past"
          ]
        },
        {
          "word_form": "ettergått",
          "tags_json": [
            "verb",
            "<PerfPart>",
            "Adj",
            "Neuter",
            "Ind",
            "Sing",
            "Masc/Fem"
          ]
        },
        {
          "word_form": "ettergåtte",
          "tags_json": [
            "verb",
            "Adj",
            "<PerfPart>",
            "Def",
            "Sing",
            "Plur"
          ]
        },
        {
          "word_form": "ettergående",
          "tags_json": [
            "verb",
            "Adj",
            "<PresPart>"
          ]
        }
      ]
    }
  ],
  "cross_reference": null,
  "definitions": [
    {
      "text": "granske kritisk",
      "translation": "examine critically",
      "examples": [
        "hun ettergår tallmaterialet"
      ]
    }
  ]
}