{
  "source_article_id": 1229,
  "lemmas": [
    {
      "lemma": "ærefrykt",
      "hgno": 0,
      "pos": "NOUN",
      "source_lemma_id": 80802,
      "is_sub_article": false,
      "primary_translation": "awe",
      "word_forms": [
        {
          "word_form": "ærefrykt",
          "tags_json": [
            "Masc",
            "m1",
            "Sing",
            "Ind"
          ]
        },
        {
          "word_form": "ærefrykten",
          "tags_json": [
            "Masc",
            "m1",
            "Sing",
            "Def"
          ]
        },
        {
          "word_form": "ærefrykter",
          "tags_json": [
            "Masc",
            "m1",
            "Plur",
            "Ind"
          ]
        },
        {
          "word_form": "ærefryktene",
          "tags_json": [
            "Masc",
            "m1",
            "Plur",
            "Def"
          ]
        }
      ]
    }
  ],
  "cross_reference": null,
  "definitions": [
    {
      "text": "dyp ærbødighet",
      "translation": "deep reverence",
      "examples": []
    }
  ]
}