{
  "source_article_id": 24908,
  "lemmas": [
    {
      "lemma": "hydrofob",
      "hgno": 0,
      "pos": "ADJ",
      "source_lemma_id": 29421,
      "is_sub_article": false,
      "primary_translation": "hydrophobic / water-repellent",
      "word_forms": [
        {
          "word_form": "hydrofob",
          "tags_json": [
            "a1",
            "Pos",
            "Masc/Fem",
            "Ind",
            "Sing"
          ]
        },
        {
          "word_form": "hydrofobe",
          "tags_json": [
            "a1",
            "Pos",
            "Plur",
            "Def",
            "Sing"
          ]
        },
        {
          "word_form": "hydrofobt",
          "tags_json": [
            "a1",
            "Pos",
            "Neuter",
            "Ind",
            "Sing"
          ]
        }
      ]
    }
  ],
  "cross_reference": null,
  "definitions": [
    {
      "text": "om stoffer: som ikke trekker til seg vann",
      "translation": "of substances: that do not absorb water",
      "examples": []
    },
    {
      "text": "vannavstøtende",
      "translation": "water-repellent",
      "examples": []
    },
    {
      "text": "motsatt hydrofil",
      "translation": "opposite of hydrophilic",
      "examples": []
    }
  ]
}