{
  "source_article_id": 2955,
  "lemmas": [
    {
      "lemma": "assortere",
      "hgno": 0,
      "pos": "VERB",
      "source_lemma_id": 3512,
      "is_sub_article": false,
      "primary_translation": "assort / stock",
      "word_forms": [
        {
          "word_form": "assortere",
          "tags_json": [
            "v2",
            "Inf"
          ]
        },
        {
          "word_form": "assorterer",
          "tags_json": [
            "v2",
            "Pres"
          ]
        },
        {
          "word_form": "assorteres",
          "tags_json": [
            "v2",
            "Inf",
            "Pass",
            "Pres"
          ]
        },
        {
          "word_form": "assorterte",
          "tags_json": [
            "v2",
            "Past",
            "Adj",
            "<PerfPart>",
            "Def",
            "Sing",
            "Plur"
          ]
        },
        {
          "word_form": "assortert",
          "tags_json": [
            "v2",
            "<PerfPart>",
            "Adj",
            "Neuter",
            "Ind",
            "Sing",
            "Masc/Fem"
          ]
        },
        {
          "word_form": "assorterende",
          "tags_json": [
            "v2",
            "Adj",
            "<PresPart>"
          ]
        },
        {
          "word_form": "assorter",
          "tags_json": [
            "v2",
            "Imp"
          ]
        }
      ]
    }
  ],
  "cross_reference": null,
  "definitions": [
    {
      "text": "forsyne med varer i høvelig utvalg, særlig i perfektum partisipp",
      "translation": "to supply with goods in a suitable selection, especially in",
      "examples": [
        "en assortert landhandel",
        "assorterte varer"
      ]
    }
  ]
}