{
  "source_article_id": 33846,
  "lemmas": [
    {
      "lemma": "langtrukken",
      "hgno": 0,
      "pos": "ADJ",
      "source_lemma_id": 39702,
      "is_sub_article": false,
      "primary_translation": "long-drawn-out / tedious",
      "word_forms": [
        {
          "word_form": "langtrukken",
          "tags_json": [
            "Pos",
            "Masc/Fem",
            "Ind",
            "Sing"
          ]
        },
        {
          "word_form": "langtrukne",
          "tags_json": [
            "Pos",
            "Plur",
            "Def",
            "Sing"
          ]
        },
        {
          "word_form": "langtrukkent",
          "tags_json": [
            "Pos",
            "Neuter",
            "Ind",
            "Sing"
          ]
        }
      ]
    }
  ],
  "cross_reference": null,
  "definitions": [
    {
      "text": "som varer lenge",
      "translation": "that lasts a long time",
      "examples": [
        "et langtrukkent hyl"
      ]
    },
    {
      "text": "langvarig og kjedsommelig",
      "translation": "long-lasting and tedious",
      "examples": [
        "en langtrukken preken"
      ]
    }
  ]
}