{
  "source_article_id": 3657,
  "lemmas": [
    {
      "lemma": "avlsproduktiv",
      "hgno": 0,
      "pos": "ADJ",
      "source_lemma_id": 4343,
      "is_sub_article": false,
      "primary_translation": "prolific in breeding",
      "word_forms": [
        {
          "word_form": "avlsproduktiv",
          "tags_json": [
            "a1",
            "Pos",
            "Masc/Fem",
            "Ind",
            "Sing"
          ]
        },
        {
          "word_form": "avlsproduktive",
          "tags_json": [
            "a1",
            "Pos",
            "Plur",
            "Def",
            "Sing"
          ]
        },
        {
          "word_form": "avlsproduktivt",
          "tags_json": [
            "a1",
            "Pos",
            "Neuter",
            "Ind",
            "Sing"
          ]
        }
      ]
    }
  ],
  "cross_reference": null,
  "definitions": [
    {
      "text": "som får tallrikt avkom",
      "translation": "that which produces numerous offspring",
      "examples": [
        "en avlsproduktiv rase"
      ]
    }
  ]
}